pyddi_xupan/__init__.py
pyddi_xupan/database_client.py
pyddi_xupan/dataset_client.py
pyddi_xupan/dblucenemapping_client.py
pyddi_xupan/enrichement_client.py
pyddi_xupan/feedback_client.py
pyddi_xupan/publication_client.py
pyddi_xupan/seo_client.py
pyddi_xupan/statistics_client.py
pyddi_xupan/term_client.py
pyddi_xupan-0.0.1.dist-info/METADATA
pyddi_xupan-0.0.1.dist-info/WHEEL
pyddi_xupan-0.0.1.dist-info/top_level.txt
pyddi_xupan-0.0.1.dist-info/RECORD
